smuls/__init__.py
smuls/main.py
smuls-0.3.0.dist-info/LICENSE
smuls-0.3.0.dist-info/METADATA
smuls-0.3.0.dist-info/WHEEL
smuls-0.3.0.dist-info/entry_points.txt
smuls-0.3.0.dist-info/top_level.txt
smuls-0.3.0.dist-info/RECORD
