Metadata-Version: 2.1
Name: smuls
Version: 0.3.0
Summary: A brief description of your package
Author: Sam_x
Classifier: Programming Language :: Python :: 3
Classifier: License :: OSI Approved :: MIT License
Classifier: Operating System :: OS Independent
Requires-Python: >=3.6
License-File: LICENSE
